{
  "allow_live_comments": true,
  "approved_at_utc": null,
  "approved_by": null,
  "archived": false,
  "author": "AllgBeamtenrecht",
  "author_flair_background_color": null,
  "author_flair_css_class": null,
  "author_flair_richtext": [],
  "author_flair_template_id": null,
  "author_flair_text": null,
  "author_flair_text_color": null,
  "author_flair_type": "text",
  "author_fullname": "t2_mqlwx1y",
  "author_patreon_flair": false,
  "author_premium": false,
  "awarders": [],
  "banned_at_utc": null,
  "banned_by": null,
  "can_gild": false,
  "can_mod_post": false,
  "category": null,
  "clicked": false,
  "content_categories": null,
  "contest_mode": false,
  "created": 1604810394,
  "created_utc": 1604781594,
  "discussion_type": null,
  "distinguished": null,
  "domain": "self.stocks",
  "downs": 0,
  "edited": 1604782111,
  "gilded": 0,
  "gildings": {},
  "hidden": false,
  "hide_score": false,
  "id": "jpxuxr",
  "is_crosspostable": false,
  "is_meta": false,
  "is_original_content": false,
  "is_reddit_media_domain": false,
  "is_robot_indexable": true,
  "is_self": true,
  "is_video": false,
  "likes": null,
  "link_flair_background_color": "",
  "link_flair_css_class": null,
  "link_flair_richtext": [],
  "link_flair_text": null,
  "link_flair_text_color": "dark",
  "link_flair_type": "text",
  "locked": false,
  "media": null,
  "media_embed": {},
  "media_only": false,
  "mod_note": null,
  "mod_reason_by": null,
  "mod_reason_title": null,
  "mod_reports": [],
  "name": "t3_jpxuxr",
  "no_follow": false,
  "num_comments": 41,
  "num_crossposts": 0,
  "num_reports": null,
  "over_18": false,
  "parent_whitelist_status": "all_ads",
  "permalink": "/r/stocks/comments/jpxuxr/china_will_be_carrying_the_global_economy_in_the/",
  "pinned": false,
  "pwls": 6,
  "quarantine": false,
  "removal_reason": null,
  "removed_by": null,
  "removed_by_category": null,
  "report_reasons": null,
  "saved": false,
  "score": 9,
  "secure_media": null,
  "secure_media_embed": {},
  "selftext": "That's how I think those next years will be. There is going to be green energy  (ICLN and friends) and  China.\n\nWhat GROWTH stocks from China would you guys recommend?  EV is very hyped right now, bit too much for my taste, feels like a bubble.\n\nMy eyes are on BZUN and JNK already. What else is there?\n\nI am looking for those smaller companies, MC of 1-10 billion. (so not the obvious big boys NIO, BABA, JD, TENCENT etc.)",
  "selftext_html": "<!-- SC_OFF --><div class=\"md\"><p>That&#39;s how I think those next years will be. There is going to be green energy  (ICLN and friends) and  China.</p>\n\n<p>What GROWTH stocks from China would you guys recommend?  EV is very hyped right now, bit too much for my taste, feels like a bubble.</p>\n\n<p>My eyes are on BZUN and JNK already. What else is there?</p>\n\n<p>I am looking for those smaller companies, MC of 1-10 billion. (so not the obvious big boys NIO, BABA, JD, TENCENT etc.)</p>\n</div><!-- SC_ON -->",
  "send_replies": true,
  "spoiler": false,
  "stickied": false,
  "subreddit": "stocks",
  "subreddit_id": "t5_2qjfk",
  "subreddit_name_prefixed": "r/stocks",
  "subreddit_subscribers": 900379,
  "subreddit_type": "public",
  "suggested_sort": null,
  "thumbnail": "",
  "title": "China will be carrying the global economy in the next couple of years. How to profit from this?",
  "top_awarded_type": null,
  "total_awards_received": 1,
  "treatment_tags": [],
  "ups": 9,
  "upvote_ratio": 0.62,
  "url": "https://www.reddit.com/r/stocks/comments/jpxuxr/china_will_be_carrying_the_global_economy_in_the/",
  "user_reports": [],
  "view_count": null,
  "visited": false,
  "whitelist_status": "all_ads",
  "wls": 6,
  "title_zh": "中国将携带全球经济在未来几年。如何从中获利？"
}
